codemind/__init__.py
codemind/__main__.py
codemind/indexing.py
codemind/parsers.py
codemind/workspace.py
codemind/tools/__init__.py
codemind/tools/analysis.py
codemind/tools/context.py
codemind/tools/dependencies.py
codemind/tools/management.py
codemind/tools/refactoring.py
codemind/tools/search.py
mcp_codemind-2.0.3.dist-info/licenses/LICENSE
mcp_codemind-2.0.3.dist-info/METADATA
mcp_codemind-2.0.3.dist-info/WHEEL
mcp_codemind-2.0.3.dist-info/entry_points.txt
mcp_codemind-2.0.3.dist-info/top_level.txt
mcp_codemind-2.0.3.dist-info/RECORD
