Metadata-Version: 2.4
Name: mcp-codemind
Version: 2.0.3
Summary: Multi-Workspace MCP Memory Server for GitHub Copilot with automatic re-indexing
Home-page: https://github.com/MrUnreal/codemind
Author: MrUnreal
Author-email: MrUnreal <mrunreal@users.noreply.github.com>
License: MIT
Project-URL: Homepage, https://github.com/MrUnreal/codemind
Project-URL: Documentation, https://github.com/MrUnreal/codemind/blob/master/README.md
Project-URL: Repository, https://github.com/MrUnreal/codemind
Project-URL: Bug Tracker, https://github.com/MrUnreal/codemind/issues
Project-URL: Changelog, https://github.com/MrUnreal/codemind/blob/master/CHANGELOG.md
Keywords: mcp,model-context-protocol,github-copilot,code-analysis,semantic-search
Classifier: Development Status :: 4 - Beta
Classifier: Intended Audience :: Developers
Classifier: License :: OSI Approved :: MIT License
Classifier: Programming Language :: Python :: 3
Classifier: Programming Language :: Python :: 3.8
Classifier: Programming Language :: Python :: 3.9
Classifier: Programming Language :: Python :: 3.10
Classifier: Programming Language :: Python :: 3.11
Classifier: Programming Language :: Python :: 3.12
Classifier: Topic :: Software Development :: Libraries :: Python Modules
Classifier: Topic :: Software Development :: Code Generators
Classifier: Topic :: Text Processing :: Indexing
Requires-Python: >=3.8
License-File: LICENSE
Requires-Dist: fastmcp<1.0.0,>=0.2.0
Requires-Dist: sentence-transformers<3.0.0,>=2.2.0
Requires-Dist: numpy<2.0.0,>=1.24.0
Requires-Dist: radon<7.0.0,>=6.0.0
Provides-Extra: dev
Requires-Dist: pytest>=7.0.0; extra == "dev"
Requires-Dist: pytest-cov>=4.0.0; extra == "dev"
Requires-Dist: black>=23.0.0; extra == "dev"
Requires-Dist: flake8>=6.0.0; extra == "dev"
Requires-Dist: mypy>=1.0.0; extra == "dev"
Dynamic: author
Dynamic: home-page
Dynamic: license-file
Dynamic: requires-python
